datahammer.py
datahammer-1.0.3.dist-info/LICENSE
datahammer-1.0.3.dist-info/LICENSE.txt
datahammer-1.0.3.dist-info/METADATA
datahammer-1.0.3.dist-info/WHEEL
datahammer-1.0.3.dist-info/top_level.txt
datahammer-1.0.3.dist-info/RECORD
