Metadata-Version: 2.1
Name: datahammer
Version: 1.0.3
Summary: This module provides an easy way to manipulate and inspect lists of data.  It was designed to handle plain data types, especially the output from parsing JSON.  It allows simple operations to be done on the items in parallel in a concise fashion.  Many features will also work on other data types.
Home-page: https://gitlab.com/n2vram/datahammer
Download-URL: https://gitlab.com/n2vram/datahammer/archive/1.0.3
Author: NVRAM
Author-email: nvram@users.sourceforge.net
License: MIT
Keywords: data,datasets,queries,JSON,resultsets,datahammer,hammer
Platform: any
Classifier: Development Status :: 5 - Production/Stable
Classifier: Intended Audience :: Developers
Classifier: License :: OSI Approved :: MIT License
Classifier: Operating System :: OS Independent
Classifier: Programming Language :: Python
Classifier: Programming Language :: Python :: 2.7
Classifier: Programming Language :: Python :: 3
Classifier: Topic :: Text Processing :: Filters
Classifier: Topic :: Utilities
Classifier: Topic :: Software Development :: Libraries :: Python Modules
License-File: LICENSE
License-File: LICENSE.txt
